{
    "comment" : "one electron calculation for initial guess of RHF",
    "out_json": "one_eig.out.json",
    "out_eigvals": "one_eigvals.bin",
    "out_eigvecs": "one_eigvecs.bin",
    "sym": "D2h",
    "molecule": [
	{"atom": "H",   "q": 0.5, "xyz": [[0,0,0.7]]},
	{"atom": "Cen", "q": 0.0, "xyz": [[0,0,0]]}],
    "basis": [
	{"type": "full",
	 "ns":   [[0,0,0]],
	 "atom":  "H",
	 "rds":  [{"irrep": "Ag", "coef": [[1], [1]]}],
	 "zeta": [0.0856947, 0.2437218, 0.571611, 1.391775, 3.607554, 10.138947, 31.821600000000004, 115.95489, 520.7466, 3511.494]},
	{"type": "full",
	 "ns":   [[0,0,1]],
	 "atom":  "H",
	 "rds":  [{"irrep": "Ag", "coef": [[1], [-1]]}],
	 "zeta": [0.046326, 0.106956, 0.257028, 0.683289, 2.130384, 9.029133]},
	{"type": "full",
	 "ns":   [[0,0,2]],
	 "atom":  "H",
	 "rds":  [{"irrep": "Ag", "coef": [[1], [1]]}],
	 "zeta": [15.0, 5.0, 1.66666666, 0.5555555555]}
    ]
}




